{"errors":[],"warnings":[],"namedChunkGroups":{"app":{"chunks":[5,0,1],"assets":["webpack-runtime-9ab9822df8d3569419c2.js","webpack-runtime-9ab9822df8d3569419c2.js.map","commons.d5ef0abb16ee382cea7f.css","commons-165e27bbd216af667925.js","commons-165e27bbd216af667925.js.map","app-d9032c62874e4c48df49.js","app-d9032c62874e4c48df49.js.map"],"children":{},"childAssets":{}},"component---src-pages-404-js":{"chunks":[0,2],"assets":["commons.d5ef0abb16ee382cea7f.css","commons-165e27bbd216af667925.js","commons-165e27bbd216af667925.js.map","component---src-pages-404-js-8eb2cc8cf6572c7f064b.js","component---src-pages-404-js-8eb2cc8cf6572c7f064b.js.map"],"children":{},"childAssets":{}},"component---src-pages-index-js":{"chunks":[0,3],"assets":["commons.d5ef0abb16ee382cea7f.css","commons-165e27bbd216af667925.js","commons-165e27bbd216af667925.js.map","component---src-pages-index-js-e00cdf145e2878bebbf7.js","component---src-pages-index-js-e00cdf145e2878bebbf7.js.map"],"children":{},"childAssets":{}},"component---src-pages-page-2-js":{"chunks":[0,4],"assets":["commons.d5ef0abb16ee382cea7f.css","commons-165e27bbd216af667925.js","commons-165e27bbd216af667925.js.map","component---src-pages-page-2-js-9e29505b2dbef9e479fc.js","component---src-pages-page-2-js-9e29505b2dbef9e479fc.js.map"],"children":{},"childAssets":{}}},"assetsByChunkName":{"app":["webpack-runtime-9ab9822df8d3569419c2.js","commons.d5ef0abb16ee382cea7f.css","commons-165e27bbd216af667925.js","app-d9032c62874e4c48df49.js"],"component---src-pages-404-js":["commons.d5ef0abb16ee382cea7f.css","commons-165e27bbd216af667925.js","component---src-pages-404-js-8eb2cc8cf6572c7f064b.js"],"component---src-pages-index-js":["commons.d5ef0abb16ee382cea7f.css","commons-165e27bbd216af667925.js","component---src-pages-index-js-e00cdf145e2878bebbf7.js"],"component---src-pages-page-2-js":["commons.d5ef0abb16ee382cea7f.css","commons-165e27bbd216af667925.js","component---src-pages-page-2-js-9e29505b2dbef9e479fc.js"]}}